sampacks/__init__.py
sampacks/funcs.py
sampacks/non_use_funcs.py
sampacks/test.py
sampacks-1.6.dist-info/METADATA
sampacks-1.6.dist-info/WHEEL
sampacks-1.6.dist-info/top_level.txt
sampacks-1.6.dist-info/RECORD
